svg2mod/__init__.py
svg2mod/cli.py
svg2mod/coloredlogger.py
svg2mod/exporter.py
svg2mod/importer.py
svg2mod/svg2mod.py
svg2mod/svg/__init__.py
svg2mod/svg/geometry.py
svg2mod/svg/svg.py
svg2mod-1.2.2.dist-info/LICENSE
svg2mod-1.2.2.dist-info/METADATA
svg2mod-1.2.2.dist-info/WHEEL
svg2mod-1.2.2.dist-info/entry_points.txt
svg2mod-1.2.2.dist-info/top_level.txt
svg2mod-1.2.2.dist-info/RECORD
